[
    {
      "clientId": 1,
      "clientName": "Sampath Kumar",
      "clientStatus": "Propreitorship",
      "address": "XYZ",
      "phone" : "123456789",
      "email" : "sampath@gmail.com",
      "loa" : "Manufacturing",
      "termLoadDate" : "01/20/2018"
    },
    {
        "clientId": 2,
        "clientName": "Sampreeth Kumar",
        "clientStatus": "Propreitorship",
        "address": "XYZ",
        "phone" : "123456789",
        "email" : "sampath@gmail.com",
        "loa" : "Manufacturing",
        "termLoadDate" : "01/20/2018"
      },
      {
        "clientId": 3,
        "clientName": "Murty Kumar",
        "clientStatus": "Propreitorship",
        "address": "XYZ",
        "phone" : "123456789",
        "email" : "sampath@gmail.com",
        "loa" : "Manufacturing",
        "termLoadDate" : "01/20/2018"
      }
  ]